{
  "lesson": {
    "id": 69
  },
  "lessonOverview": {
    "title": "LRW Test",
    "topic": "P3B: Listening, Reading, Writing Test",
    "resources": {
      "studentBook": {
        "pages": "",
        "activities": []
      },
      "activityBook": {
        "pages": "",
        "activities": []
      },
      "phonicsBook": {
        "pages": "",
        "activities": []
      },
      "homework": null,
      "materials": []
    },
    "vocabulary": [],
    "structures": [],
    "phonics": []
  },
  "lessonOutcomes": [],
  "languageTransferAnalysis": [],
  "lessonPlan": null
}